greeksoft/__init__.py
greeksoft/greeksoft.py
greeksoft-0.1.1.dist-info/licenses/LICENSE
greeksoft-0.1.1.dist-info/METADATA
greeksoft-0.1.1.dist-info/WHEEL
greeksoft-0.1.1.dist-info/top_level.txt
greeksoft-0.1.1.dist-info/RECORD
