Metadata-Version: 2.4
Name: greeksoft
Version: 0.1.1
Summary: The official Python client for communicating with Greeksoft's CTCL Application API
Author: Greek_dev_Team
Author-email: greeksoftapi@greeksoft.co.in
License: MIT License
License-File: LICENSE
Requires-Dist: requests>=2.32.3
Requires-Dist: pandas>=1.19.5
Requires-Dist: websocket-client>=1.8.0
Dynamic: author
Dynamic: author-email
Dynamic: description
Dynamic: description-content-type
Dynamic: license
Dynamic: license-file
Dynamic: requires-dist
Dynamic: summary
